{
    "AX": {
        "error": 0.004171458615790776, 
        "filter_outliers_dict": {
            "filter_outliers": true, 
            "iterations": 1, 
            "std_devs": 2
        }, 
        "fit": "average", 
        "value": 0.042903380970334845
    }, 
    "CDD": {
        "error": 2.4703242891869865e-06, 
        "filter_outliers_dict": {
            "filter_outliers": true, 
            "iterations": 1, 
            "std_devs": 10
        }, 
        "fit": "average", 
        "value": 5.004128465080767e-06
    }, 
    "H1": {
        "error": 0.0034554509879276374, 
        "filter_outliers_dict": {
            "filter_outliers": true, 
            "iterations": 1, 
            "std_devs": 2
        }, 
        "fit": "average", 
        "value": -0.050941964846496636
    }, 
    "H2": {
        "error": 0.003703648904407514, 
        "filter_outliers_dict": {
            "filter_outliers": true, 
            "iterations": 1, 
            "std_devs": 2
        }, 
        "fit": "average", 
        "value": 0.06693183139694005
    }, 
    "L1": {
        "error": 0.0017158751006182296, 
        "filter_outliers_dict": {
            "filter_outliers": true, 
            "iterations": 1, 
            "std_devs": 2
        }, 
        "fit": "average", 
        "value": 0.0005416405376701308
    }, 
    "L2": {
        "error": 0.003933069202668391, 
        "filter_outliers_dict": {
            "filter_outliers": true, 
            "iterations": 1, 
            "std_devs": 2
        }, 
        "fit": "average", 
        "value": 0.14253444513584948
    }
}